tks/__init__.py
tks/__main__.py
tks/lex.py
tks/parser.py
tks2html-1.0.0.dist-info/DESCRIPTION.rst
tks2html-1.0.0.dist-info/METADATA
tks2html-1.0.0.dist-info/RECORD
tks2html-1.0.0.dist-info/WHEEL
tks2html-1.0.0.dist-info/entry_points.txt
tks2html-1.0.0.dist-info/metadata.json
tks2html-1.0.0.dist-info/top_level.txt
