Metadata-Version: 2.0
Name: tks2html
Version: 1.0.0
Summary: Covert Kscript into highlight code HTML file
Home-page: https://github.com/LeslieZhu/tks
Author: Leslie Zhu
Author-email: pythonisland@gmail.com
License: GPL
Keywords: tks,kscript,tks2html
Platform: linux
Classifier: Programming Language :: Python
Classifier: Programming Language :: Python :: 2.7
Classifier: Environment :: Other Environment
Classifier: Intended Audience :: Developers
Classifier: Operating System :: OS Independent
Classifier: Topic :: Software Development :: Libraries :: Python Modules
Classifier: Topic :: Text Processing :: Linguistic
